{
  "aspect_ratio": "16-9",
  "desc": "Common Voice est une initiative de Mozilla pour apprendre aux machines comment les humains parlent vraiment.",
  "highres_image": "home-fr/card_12/common-voice-high-res.27423e936f12.png",
  "image": "home-fr/card_12/common-voice.65fbb8a26b45.png",
  "link_url": "https://voice.mozilla.org/fr?utm_source=www.mozilla.org&utm_medium=referral&utm_campaign=homepage&utm_content=card",
  "size": "small",
  "tag_label": "Technologies émergentes",
  "title": "Common Voice, un projet en bonne voie"
}