{
  "aspect_ratio": "3-2",
  "desc": "Every Monday, we dig into the news and give you the tools, tips and tricks needed to cut the crap and find the truth.",
  "highres_image": "home-2020-oct/card_8/card8-high-res.fdabeef65dd5.jpg",
  "image": "home-2020-oct/card_8/card8.cc07165daf82.jpg",
  "link_url": "https://getpocket.com/explore/item/u-s-election-2020-how-to-spot-and-fight-misinformation, https://foundation.mozilla.org/en/blog/tags/misinformation-monday/",
  "size": "small",
  "tag_label": "Mozilla Foundation",
  "title": "Misinfo Mondays"
}