{
  "aspect_ratio": "3-2",
  "desc": "These 13 extensions are here to make remote work and school a little easier and more productive.",
  "highres_image": "home-2019/card_8/productivity-high-res.9659ecc72aeb.jpg",
  "image": "home-2019/card_8/productivity.f940c6182a90.jpg",
  "link_url": "https://blog.mozilla.org/firefox/firefox-extensions-work-from-home?utm_source=www.mozilla.org&utm_medium=referral&utm_campaign=homepage&utm_content=card",
  "size": "medium",
  "tag_label": "Extensions",
  "title": "Productivity boosters"
}