{
  "aspect_ratio": "16-9",
  "desc": "Pocket has the best new perspectives, hidden gems, fascinating deep-dives and timeless classics any time you want a break.",
  "highres_image": "home-2019/card_1/reads-high-res.498adb3b0d3e.png",
  "image": "home-2019/card_1/reads.9b652ec5bff6.png",
  "link_url": "https://getpocket.com/explore/?utm_source=www.mozilla.org&utm_medium=referral&utm_campaign=homepage&utm_content=card",
  "size": "large",
  "tag_label": "Pocket",
  "title": "Discover the best reads"
}