{
  "aspect_ratio": "16-9",
  "desc": "Bedenken wegen des nächsten Datenlecks? Durchatmen, Tipps durchlesen, Kuchen essen!",
  "highres_image": "home-de/card_9/tips-high-res.0d70fb1ea7c1.png",
  "image": "home-de/card_9/tips.276b3867fdd6.png",
  "link_url": "https://blog.mozilla.org/internetcitizen/de/2018/10/29/sichere-zuallererst-deine-passwoerter/?utm_source=www.mozilla.org&utm_medium=referral&utm_campaign=homepage-de&utm_content=card",
  "size": "small",
  "tag_label": "Tipps",
  "title": "Das 1x1 des sicheren Passworts"
}