{
  "aspect_ratio": "16-9",
  "desc": "Gut sortiert durch das Web. So bietet Dir jeder neue Tab den perfekten Deal aus Überblick, Information und Inspiration.",
  "highres_image": "home-de/card_9/new-tab-high-res.9220a42e6b94.png",
  "image": "home-de/card_9/new-tab.d70f121cfe20.png",
  "link_url": "https://blog.mozilla.org/firefox/de/deine-eigene-firefox-startseite-unter-neuer-tab/?utm_source=www.mozilla.org&utm_medium=referral&utm_campaign=homepage-de&utm_content=card",
  "size": "small",
  "tag_label": "Firefox Browser",
  "title": "Neuer Tab: Die Startseite, die was kann"
}