{
  "aspect_ratio": "16-9",
  "desc": "So holst du dir Firefox Reality auf dein Virtual-Reality-Headset.",
  "highres_image": "home-de/card_10/firefox-reality-high-res.dc96010ec4a4.png",
  "image": "home-de/card_10/firefox-reality.a4f98f3055cb.png",
  "link_url": "https://blog.mozilla.org/firefox/de/firefox-reality-vr-headset-oculus-go/?utm_source=www.mozilla.org&utm_medium=referral&utm_campaign=homepage&utm_content=card",
  "size": "small",
  "tag_label": "Emerging Tech",
  "title": "Mit Firefox durch virtuelle Welten"
}